humongous/__init__.py
humongous/plugin.py
humongous-1.3.0.dist-info/DESCRIPTION.rst
humongous-1.3.0.dist-info/METADATA
humongous-1.3.0.dist-info/RECORD
humongous-1.3.0.dist-info/WHEEL
humongous-1.3.0.dist-info/entry_points.txt
humongous-1.3.0.dist-info/metadata.json
humongous-1.3.0.dist-info/pbr.json
humongous-1.3.0.dist-info/top_level.txt
