Metadata-Version: 2.0
Name: humongous
Version: 1.3.0
Summary: Mongo database mocking with fixtures
Home-page: https://github.com/mdomke/humongous
Author: Collins GmbH & Co. KG
Author-email: mdomke@me.com
License: MIT
Platform: UNKNOWN
Classifier: Development Status :: 5 - Production/Stable
Classifier: Environment :: Console
Classifier: Intended Audience :: Developers
Classifier: License :: OSI Approved :: MIT License
Classifier: Operating System :: POSIX :: Linux
Classifier: Operating System :: MacOS :: MacOS X
Classifier: Programming Language :: Python
Classifier: Programming Language :: Python :: 2
Classifier: Programming Language :: Python :: 2.7
Classifier: Programming Language :: Python :: 3
Classifier: Programming Language :: Python :: 3.4
Classifier: Topic :: Database
Classifier: Topic :: Software Development :: Libraries
Requires-Dist: mongomock (>=2.3,<3.0.0)
Requires-Dist: pymongo
Requires-Dist: pytest (>=2.5.2)
Requires-Dist: pyyaml
